Workbook

Sheet Assessment
A1: HENHAREN REID — EXECUTIVE SITUATIONAL JUDGMENT BATTERY
A2: Instructions: For each scenario below, review the dilemma and select your chosen course of action in Column D (Dropdown). Each option carries distinct trade-offs.
A3: Scenario # | B3: Context & Dilemma | C3: Strategic Options (A - D) | D3: Candidate Selection
A4: Scenario 1 | B4: Capital Payout vs. Unseen Structural Wear Situation: You are CEO of an infrastructure firm. Following a successful turnaround, a promised £120m dividend payout and £4m manager bonus pool are due next week. A new structural inspection reveals hidden sub-surface fatigue at your primary distribution hub. It is certified safe today (<1% annual failure risk), but a full repair will cost £110m over 3 years. Dilemma: Paying the dividend preserves credit rating, pension yields, and staff retention, but forces high-interest commercial borrowing later for repairs. Cancelling it funds structural safety immediately, but triggers an instant credit downgrade, executive resignations, and cuts to pensioner income. | C4: A) Pay a 50% dividend (£60m) and reduced bonuses; deploy £60m to immediate repairs and apply for state infrastructure matching grants. B) Cancel the dividend and bonuses entirely; reallocate all £120m to an immediate asset overhaul and accept the credit rating drop. C) Proceed with the full £120m payout as promised to protect credit and retention; secure commercial bank loans over 24 months for repairs. D) Lock funds in a 12-month repair escrow; issue long-dated equity warrants to managers in lieu of cash bonuses. | D4: Option C
A5: Scenario 2 | B5: Remote Disaster Triage (Emergency Logistics) Situation: You lead an international disaster response team after an earthquake. Roads are cut, and you have one heavy-lift helicopter for the next 72 hours. Dilemma: Site Alpha (makeshift clinic) has 120 injured patients running out of surgical supplies (14 imminent deaths). Site Beta (isolated village) has 450 civilians with zero food facing starvation and violent civil unrest. Your veteran pilot refuses to fly into Alpha's unlit mountain ravine at dusk. | C5: A) Stand down night flights until military peacekeepers provide armed escort corridors at dawn, delaying delivery by 24 hours. B) Fly the first sorties to Beta to prevent riots, using the political goodwill to negotiate safe ground passage to Alpha later. C) Order the pilot to fly to Alpha immediately using night-vision gear, threatening contract termination if he refuses. D) Drop 50/50 supplies at a neutral midway point, requiring local elders from both sites to arrange mule transport across contested lines. | D5: Option A
A6: Scenario 3 | B6: Maritime Search & Rescue Asset Deployment Situation: You are Director of Coastguard Operations during a winter storm. Two vessels are in critical distress at opposite edges of your sector with only one all-weather cutter available. Dilemma: A passenger ferry with 180 people is drifting toward rocks (15% grounding risk, tugboats 4 hours away). An overturned trawler has 6 crew members trapped in a freezing air pocket with a confirmed 90-minute survival limit. | C6: A) Send the cutter to the trawler to guarantee rescue of the 6 trapped crew within 90 minutes, relying on commercial tugs to reach the ferry. B) Order a nearby foreign container ship to divert to the ferry while your cutter rescues the trawler crew. C) Escort the 180-passenger ferry to port, accepting the certain loss of the 6 trawler crew members. D) Run a 20-minute surface search at the trawler, then break off at maximum speed to intercept the ferry. | D6: Option B
A7: Scenario 4 | B7: Clean Energy Transmission vs. Historical Land Treaty Situation: You head a national energy transition authority building a £1.8B power line to connect offshore wind to 3 million homes and cut national carbon emissions by 8%. Dilemma: The final 12 miles cross unceded ancestral land protected by a historic treaty. Re-routing around the boundary costs £240m and adds a 3-year delay, requiring coal plants to run during the interim. | C7: A) Approve the £240m bypass route and 3-year delay, accepting higher short-term emissions to protect indigenous treaty rights. B) Exercise state legal powers to build on schedule through the corridor, paying 200% statutory financial compensation into community trust funds. C) Offer the community a 20% perpetual royalty on line transmission revenues in exchange for voluntary immediate access. D) Underground the cables through the protected corridor at a cost of £140m, splitting the cost overrun with regional taxpayers. | D7: Option A
A8: Scenario 5 | B8: Junior Talent Pipeline vs. AI Profit Surge Situation: You are Managing Partner of an elite 2,000-person commercial advisory and law firm. A new AI engine executes discovery, contract drafting, and research in minutes at 95% lower cost. Dilemma: Clients demand a 35% fee cut. Cutting junior associate intake from 250 down to 25 saves £42m annually and lifts partner profits by 28%. However, cutting junior hiring eliminates the firm's cognitive apprenticeship model—meaning in 15 years the firm will have no seasoned partners capable of auditing the AI, handling high-stakes client negotiations, or leading complex litigation. | C8: A) Restrict AI substitution; maintain full junior hiring (250/yr) to protect 20-year institutional judgment, absorbing a 20% near-term client revenue defection. B) Spin off the AI tool into a separate low-cost legal-tech volume business; keep the parent partnership 100% bespoke and human-led at premium rates. C) Cut junior intake by 90% immediately, pass fee cuts to clients, and harvest the 28% profit lift for current equity partners. D) Deploy the AI across all client work, keep 50% junior intake, and fund a £15m 'Deep Advisory & Edge-Case Academy' using partner profits. | D8: Option A
A9: Scenario 6 | B9: Clinical Safety Anomaly vs. Essential Antibiotic Delay Situation: You are Chief Medical Officer of a pharmaceutical firm completing Phase III trials for an antibiotic against drug-resistant hospital superbugs. The drug cures 88% of cases and is projected to save 40,000 lives annually. Dilemma: Final subgroup data reveals a rare, unexplainable liver toxicity signal in 0.4% of patients with pre-existing metabolic conditions (not statistically significant under regulatory disclosure rules). Halting the launch for an 18-month safety trial will cause an estimated 60,000 preventable deaths from untreated superbug infections during the delay. | C9: A) File for approval immediately with a voluntary warning label restricting use in patients with metabolic conditions, protecting the vulnerable without delaying general access. B) Submit all unredacted trial data and the 0.4% signal directly to health regulators, leaving the risk determination to public authorities despite review delays. C) Launch immediately under standard endpoints to maximize lives saved; set up a voluntary post-market registry to track liver telemetry in real time. D) Halt the filing immediately to run the 18-month safety trial, accepting the write-down and the clinical delay to guarantee zero toxic risk. | D9: Option C

Sheet Scoring_Matrix
A1: EXECUTIVE CARDINAL VIRTUE DIAGNOSTIC — SCORING ENGINE REFERENCE
A2: Key (Lookup) | B2: Scenario # | C2: Option | D2: Net Prudence (P) | E2: Net Fortitude (F) | F2: Net Temperance (T) | G2: Net Justice (J) | H2: Virtues Present / Breached | I2: Behavioral Trait Tag
A3: Q1-Option A | B3: 1 | C3: Option A | D3: 2 | E3: -2 | F3: 1 | G3: 0 | H3: +2P, +1T / -2F | I3: Adaptive Compromise
A4: Q1-Option B | B4: 1 | C4: Option B | D4: 1 | E4: 2 | F4: 0 | G4: -2 | H4: +2F, +1P / -2J | I4: Aggressive De-risking
A5: Q1-Option C | B5: 1 | C5: Option C | D5: 1 | E5: -2 | F5: -1 | G5: 2 | H5: +2J, +1P / -2F, -1T | I5: Fiduciary Continuity
A6: Q1-Option D | B6: 1 | C6: Option D | D6: -2 | E6: 0 | F6: 2 | G6: 2 | H6: +2T, +2J / -2P | I6: Delayed Structural Reform
A7: Q2-Option A | B7: 2 | C7: Option A | D7: 0 | E7: -2 | F7: 2 | G7: 0 | H7: +2T / -2F | I7: Bureaucratic Risk Avoidance
A8: Q2-Option B | B8: 2 | C8: Option B | D8: 2 | E8: 0 | F8: 0 | G8: -2 | H8: +2P / -2J | I8: Systems-Level Prioritization
A9: Q2-Option C | B9: 2 | C9: Option C | D9: -2 | E9: 2 | F9: 0 | G9: 1 | H9: +2F, +1J / -2P | I9: Decisive Moral Intervention
A10: Q2-Option D | B10: 2 | C10: Option D | D10: -2 | E10: 0 | F10: 0 | G10: 2 | H10: +2J / -2P | I10: Mathematical Egalitarianism
A11: Q3-Option A | B11: 3 | C11: Option A | D11: -2 | E11: 2 | F11: 0 | G11: 1 | H11: +2F, +1J / -2P | I11: Direct Ethical Focus
A12: Q3-Option B | B12: 3 | C12: Option B | D12: 2 | E12: 0 | F12: 0 | G12: -2 | H12: +2P / -2J | I12: Asymmetric Risk Leverage
A13: Q3-Option C | B13: 3 | C13: Option C | D13: 2 | E13: -1 | F13: 0 | G13: -2 | H13: +2P / -2J, -1F | I13: Maximized Welfare Utility
A14: Q3-Option D | B14: 3 | C14: Option D | D14: 1 | E14: -2 | F14: 1 | G14: 0 | H14: +1T, +1P / -2F | I14: Hedged Compromise
... A26: Q6-Option D | B26: 6 | C26: Option D | D26: -2 | E26: 2 | F26: 0 | G26: 2 | H26: +2J, +2F / -2P | I26: Absolute Precautionary Stance

Sheet Results_Dashboard
A1: EXECUTIVE CHARACTER & DECISION ARCHITECTURE DASHBOARD
A3: 1. NET CARDINAL VIRTUE VECTORS (-12 to +12)
A4: Cardinal Virtue | B4: Net Score | C4: Scale Range | D4: Diagnostic Interpretation
A5: Prudence (Phronesis) | B5: =SUMPRODUCT((Scoring_Matrix!$B$3:$B$26=1)*(Scoring_Matrix!$C$3:$C$26=Assessment!$D$4), Scoring_Matrix!$D$3:$D$26) + SUMPRODUCT((Scoring_Matrix!$B$3:$B$26=2)*(Scoring_Matrix!$C$3:$C$26=Assessment!$D$5), Scoring_Matrix!$D$3:$D$26) + SUMPRODUCT((Scoring_Matrix!$B$3:$B$26=3)*(Scoring_Matrix!$C$3:$C$26=Assessment!$D$6), Scoring_Matrix!$D$3:$D$26) + SUMPRODUCT((Scoring_Matrix!$B$3:$B$26=4)*(Scoring_Matrix!$C$3:$C$26=Assessment!$D$7), Scoring_Matrix!$D$3:$D$26) + SUMPRODUCT((Scoring_Matrix!$B$3:$B$26=5)*(Scoring_Matrix!$C$3:$C$26=Assessment!$D$8), Scoring_Matrix!$D$3:$D$26) + SUMPRODUCT((Scoring_Matrix!$B$3:$B$26=6)*(Scoring_Matrix!$C$3:$C$26=Assessment!$D$9), Scoring_Matrix!$D$3:$D$26) -> 1 | C5: -12 to +12 | D5: Systemic foresight vs. immediate utility trade-off
A6: Fortitude (Moral Courage) | B6: =SUMPRODUCT((Scoring_Matrix!$B$3:$B$26=1)*(Scoring_Matrix!$C$3:$C$26=Assessment!$D$4), Scoring_Matrix!$E$3:$E$26) + SUMPRODUCT((Scoring_Matrix!$B$3:$B$26=2)*(Scoring_Matrix!$C$3:$C$26=Assessment!$D$5), Scoring_Matrix!$E$3:$E$26) + SUMPRODUCT((Scoring_Matrix!$B$3:$B$26=3)*(Scoring_Matrix!$C$3:$C$26=Assessment!$D$6), Scoring_Matrix!$E$3:$E$26) + SUMPRODUCT((Scoring_Matrix!$B$3:$B$26=4)*(Scoring_Matrix!$C$3:$C$26=Assessment!$D$7), Scoring_Matrix!$E$3:$E$26) + SUMPRODUCT((Scoring_Matrix!$B$3:$B$26=5)*(Scoring_Matrix!$C$3:$C$26=Assessment!$D$8), Scoring_Matrix!$E$3:$E$26) + SUMPRODUCT((Scoring_Matrix!$B$3:$B$26=6)*(Scoring_Matrix!$C$3:$C$26=Assessment!$D$9), Scoring_Matrix!$E$3:$E$26) -> -1 | C6: -12 to +12 | D6: Willingness to absorb friction and direct accountability
A7: Temperance (Restraint) | B7: =SUMPRODUCT((Scoring_Matrix!$B$3:$B$26=1)*(Scoring_Matrix!$C$3:$C$26=Assessment!$D$4), Scoring_Matrix!$F$3:$F$26) + SUMPRODUCT((Scoring_Matrix!$B$3:$B$26=2)*(Scoring_Matrix!$C$3:$C$26=Assessment!$D$5), Scoring_Matrix!$F$3:$F$26) + SUMPRODUCT((Scoring_Matrix!$B$3:$B$26=3)*(Scoring_Matrix!$C$3:$C$26=Assessment!$D$6), Scoring_Matrix!$F$3:$F$26) + SUMPRODUCT((Scoring_Matrix!$B$3:$B$26=4)*(Scoring_Matrix!$C$3:$C$26=Assessment!$D$7), Scoring_Matrix!$F$3:$F$26) + SUMPRODUCT((Scoring_Matrix!$B$3:$B$26=5)*(Scoring_Matrix!$C$3:$C$26=Assessment!$D$8), Scoring_Matrix!$F$3:$F$26) + SUMPRODUCT((Scoring_Matrix!$B$3:$B$26=6)*(Scoring_Matrix!$C$3:$C$26=Assessment!$D$9), Scoring_Matrix!$F$3:$F$26) -> 1 | C7: -12 to +12 | D7: Resistance to short-term greed, ego, and over-extraction
A8: Justice (Fairness & Truth) | B8: =SUMPRODUCT((Scoring_Matrix!$B$3:$B$26=1)*(Scoring_Matrix!$C$3:$C$26=Assessment!$D$4), Scoring_Matrix!$G$3:$G$26) + SUMPRODUCT((Scoring_Matrix!$B$3:$B$26=2)*(Scoring_Matrix!$C$3:$C$26=Assessment!$D$5), Scoring_Matrix!$G$3:$G$26) + SUMPRODUCT((Scoring_Matrix!$B$3:$B$26=3)*(Scoring_Matrix!$C$3:$C$26=Assessment!$D$6), Scoring_Matrix!$G$3:$G$26) + SUMPRODUCT((Scoring_Matrix!$B$3:$B$26=4)*(Scoring_Matrix!$C$3:$C$26=Assessment!$D$7), Scoring_Matrix!$G$3:$G$26) + SUMPRODUCT((Scoring_Matrix!$B$3:$B$26=5)*(Scoring_Matrix!$C$3:$C$26=Assessment!$D$8), Scoring_Matrix!$G$3:$G$26) + SUMPRODUCT((Scoring_Matrix!$B$3:$B$26=6)*(Scoring_Matrix!$C$3:$C$26=Assessment!$D$9), Scoring_Matrix!$G$3:$G$26) -> 2 | C8: -12 to +12 | D8: Distributive equity and commitment to covenants
A10: 2. SCENARIO-BY-SCENARIO RESPONSE AUDIT
A11: Scenario # | B11: Dilemma Context | C11: Selected Choice | D11: Behavioral Trait Tag | E11: Virtue Vector Impact (+ / -)
A12: Scenario 1 | B12: Capital Payout vs. Asset Wear | C12: =Assessment!D4 -> Option C | D12: =INDEX(Scoring_Matrix!$I$3:$I$26, MATCH("Q1-"&Assessment!D4, Scoring_Matrix!$A$3:$A$26, 0)) -> Fiduciary Continuity | E12: =INDEX(Scoring_Matrix!$H$3:$H$26, MATCH("Q1-"&Assessment!D4, Scoring_Matrix!$A$3:$A$26, 0)) -> +2J, +1P / -2F, -1T
A13: Scenario 2 | B13: Remote Disaster Triage | C13: =Assessment!D5 -> Option A | D13: =INDEX(Scoring_Matrix!$I$3:$I$26, MATCH("Q2-"&Assessment!D5, Scoring_Matrix!$A$3:$A$26, 0)) -> Bureaucratic Risk Avoidance | E13: =INDEX(Scoring_Matrix!$H$3:$H$26, MATCH("Q2-"&Assessment!D5, Scoring_Matrix!$A$3:$A$26, 0)) -> +2T / -2F
A14: Scenario 3 | B14: Maritime Search & Rescue | C14: =Assessment!D6 -> Option B | D14: =INDEX(Scoring_Matrix!$I$3:$I$26, MATCH("Q3-"&Assessment!D6, Scoring_Matrix!$A$3:$A$26, 0)) -> Asymmetric Risk Leverage | E14: =INDEX(Scoring_Matrix!$H$3:$H$26, MATCH("Q3-"&Assessment!D6, Scoring_Matrix!$A$3:$A$26, 0)) -> +2P / -2J
A15: Scenario 4 | B15: Clean Energy vs. Land Treaty | C15: =Assessment!D7 -> Option A | D15: =INDEX(Scoring_Matrix!$I$3:$I$26, MATCH("Q4-"&Assessment!D7, Scoring_Matrix!$A$3:$A$26, 0)) -> Uncompromising Deontology | E15: =INDEX(Scoring_Matrix!$H$3:$H$26, MATCH("Q4-"&Assessment!D7, Scoring_Matrix!$A$3:$A$26, 0)) -> +2J, +1F / -2P
A16: Scenario 5 | B16: Junior Talent vs. AI Surge | C16: =Assessment!D8 -> Option A | D16: =INDEX(Scoring_Matrix!$I$3:$I$26, MATCH("Q5-"&Assessment!D8, Scoring_Matrix!$A$3:$A$26, 0)) -> Guild Protectionism | E16: =INDEX(Scoring_Matrix!$H$3:$H$26, MATCH("Q5-"&Assessment!D8, Scoring_Matrix!$A$3:$A$26, 0)) -> +2F, +2J / -2P
A17: Scenario 6 | B17: Clinical Anomaly vs. Antibiotic | C17: =Assessment!D9 -> Option C | D17: =INDEX(Scoring_Matrix!$I$3:$I$26, MATCH("Q6-"&Assessment!D9, Scoring_Matrix!$A$3:$A$26, 0)) -> Maximum Life Preservation | E17: =INDEX(Scoring_Matrix!$H$3:$H$26, MATCH("Q6-"&Assessment!D9, Scoring_Matrix!$A$3:$A$26, 0)) -> +2P / -2J
A19: 3. PLATFORM INTEGRATION & 3-DOMAIN TRIANGULATION
A20: Domain 1: How They Think (CPP / SST) | B20: Cross-references Net Prudence with Cognadev cognitive complexity band (Level 2-5). High CPP with low Prudence flags cynical optimization.
A21: Domain 2: How They Show Up (ZF / Hogan) | B21: Cross-references Net Fortitude & Temperance. Negative Fortitude flags Cautious/Dutiful derailers; negative Temperance flags Bold/Mischievous risk.
A22: Domain 3: How They Connect (CTS ONA) | B22: Cross-references Net Justice with ONA network centrality. Negative Justice flags structural silo gatekeeping and transactional erosion.
